picker/__init__.py
picker/admin.py
picker/apps.py
picker/conf.py
picker/exceptions.py
picker/forms.py
picker/importers.py
picker/utils.py
picker/management/__init__.py
picker/management/commands/__init__.py
picker/management/commands/import_picks.py
picker/migrations/0001_initial.py
picker/migrations/0002_auto_20160720_0917.py
picker/migrations/0003_auto_20180801_0800.py
picker/migrations/0004_auto_20180802_1515.py
picker/migrations/0005_auto_20180804_0926.py
picker/migrations/0006_auto_20180824_1356.py
picker/migrations/0007_auto_20180828_1855.py
picker/migrations/0008_auto_20180902_1428.py
picker/migrations/0009_auto_20181127_1329.py
picker/migrations/0010_auto_20181202_1240.py
picker/migrations/0011_team_notes.py
picker/migrations/0012_auto_20191224_1707.py
picker/migrations/0013_alter_tv_len.py
picker/migrations/0014_league_is_active.py
picker/migrations/0015_alter_for_big_int.py
picker/migrations/0016_picker.py
picker/migrations/__init__.py
picker/models/__init__.py
picker/models/picks.py
picker/models/sports.py
picker/templates/picker/_base/.DS_Store
picker/templates/picker/_base/group_select.html
picker/templates/picker/_base/score_strip.html
picker/templates/picker/_base/season_nav.html
picker/templates/picker/_base/season_nav_all.html
picker/templates/picker/_base/team_pick_field.html
picker/templates/picker/_base/unavailable.html
picker/templates/picker/_base/manage/game.html
picker/templates/picker/_base/manage/home.html
picker/templates/picker/_base/manage/results.html
picker/templates/picker/_base/manage/season.html
picker/templates/picker/_base/picks/make.html
picker/templates/picker/_base/picks/season.html
picker/templates/picker/_base/picks/show.html
picker/templates/picker/_base/results/results.html
picker/templates/picker/_base/results/season.html
picker/templates/picker/_base/roster/picker.html
picker/templates/picker/_base/roster/season.html
picker/templates/picker/_base/schedule/season.html
picker/templates/picker/_base/teams/detail.html
picker-3.0.0.dist-info/licenses/LICENSE
picker-3.0.0.dist-info/METADATA
picker-3.0.0.dist-info/WHEEL
picker-3.0.0.dist-info/top_level.txt
picker-3.0.0.dist-info/RECORD
