Metadata-Version: 2.4
Name: picker
Version: 3.0.0
Summary: A Django sports picker app
Author-email: David Krauth <dakrauth@gmail.com>
License-Expression: MIT
Project-URL: Homepage, https://github.com/dakrauth/django-picker
Keywords: django,sports,football
Classifier: Environment :: Web Environment
Classifier: Framework :: Django
Classifier: Framework :: Django :: 5.1
Classifier: Framework :: Django :: 5.2
Classifier: Framework :: Django :: 6.0
Classifier: Programming Language :: Python
Classifier: Programming Language :: Python :: 3
Classifier: Programming Language :: Python :: 3.11
Classifier: Programming Language :: Python :: 3.12
Classifier: Programming Language :: Python :: 3.12
Requires-Python: >=3.11
License-File: LICENSE
Requires-Dist: Django>=5.1
Requires-Dist: django-bootstrap5
Requires-Dist: Pillow>=11.3.0
Requires-Dist: python-dateutil>=2.8.1
Provides-Extra: test
Requires-Dist: pytest; extra == "test"
Requires-Dist: coverage; extra == "test"
Requires-Dist: pytest-django; extra == "test"
Requires-Dist: pytest-cov; extra == "test"
Requires-Dist: freezegun; extra == "test"
Provides-Extra: dev
Requires-Dist: tox; extra == "dev"
Requires-Dist: build; extra == "dev"
Requires-Dist: ipython; extra == "dev"
Requires-Dist: twine; extra == "dev"
Requires-Dist: ruff; extra == "dev"
Requires-Dist: ipdb; extra == "dev"
Requires-Dist: django-extensions; extra == "dev"
Requires-Dist: pytest-sugar; extra == "dev"
Requires-Dist: pytest-clarity; extra == "dev"
Dynamic: license-file
